LICENSE.txt
MANIFEST.in
README.md
README.rst
requirements-dev.txt
setup.cfg
setup.py
saws/__init__.py
saws/commands.py
saws/completer.py
saws/config.py
saws/data_util.py
saws/keys.py
saws/lexer.py
saws/logger.py
saws/main.py
saws/options.py
saws/resources.py
saws/saws.py
saws/saws.shortcuts
saws/sawsrc
saws/style.py
saws/toolbar.py
saws/utils.py
saws.egg-info/PKG-INFO
saws.egg-info/SOURCES.txt
saws.egg-info/dependency_links.txt
saws.egg-info/entry_points.txt
saws.egg-info/requires.txt
saws.egg-info/top_level.txt
saws/data/OPTIONS.txt
saws/data/RESOURCES_SAMPLE.txt
saws/data/SOURCES.txt
saws/resource/__init__.py
saws/resource/bucket.py
saws/resource/bucket_names.py
saws/resource/bucket_uris.py
saws/resource/instance_ids.py
saws/resource/instance_tag_keys.py
saws/resource/instance_tag_values.py
saws/resource/resource.py
scratch/__init__.py
scratch/auto_enum_number.py
scratch/completer.py
scratch/config.py
scratch/option.py
scratch/test_resources.py
scratch/option/__init__.py
scratch/option/ec2_states.py
scratch/option/option.py
tests/__init__.py
tests/compat.py
tests/run_tests.py
tests/test_cli.py
tests/test_commands.py
tests/test_completer.py
tests/test_keys.py
tests/test_options.py
tests/test_resources.py
tests/test_saws.py
tests/test_toolbar.py