Metadata-Version: 1.1
Name: saws
Version: 0.4.3
Summary: SAWS: A Supercharged AWS Command Line Interface (CLI)
Home-page: https://github.com/donnemartin/saws
Author: Donne Martin
Author-email: donne.martin@gmail.com
License: Apache License 2.0
Download-URL: https://pypi.python.org/pypi/saws
Platform: UNKNOWN
Classifier: Intended Audience :: Developers
Classifier: Intended Audience :: System Administrators
Classifier: License :: OSI Approved :: Apache Software License
Classifier: Natural Language :: English
Classifier: Programming Language :: Python
Classifier: Programming Language :: Python :: 2.6
Classifier: Programming Language :: Python :: 2.7
Classifier: Programming Language :: Python :: 3
Classifier: Programming Language :: Python :: 3.3
Classifier: Programming Language :: Python :: 3.4
Classifier: Topic :: Software Development
Classifier: Topic :: Software Development :: Libraries :: Python Modules
